dvpodolyak_hw1/__init__.py
dvpodolyak_hw1-0.1.2.dist-info/METADATA
dvpodolyak_hw1-0.1.2.dist-info/WHEEL
dvpodolyak_hw1-0.1.2.dist-info/RECORD
